{"exportedAt":"2026-03-01T17:49:53.635743","version":"2.0","timestamp":1772387393635,"metadata":{"totalMembers":20,"membersAnalyzed":20,"averageElectionPossibility":"28.6","totalPolls":17,"dataSourcesCount":3,"membersByParty":{"더불어민주당":9,"국민의힘":7,"개혁신당":1,"무소속":3},"analysisVersion":"v2.0"},"members":[{"id":"member_001","name":"정청래","party":"더불어민주당","district":"서울 종로구","timestamp":1772387384110,"analyzedAt":"2026-03-01T17:49:44.110281","electionPossibility":"43.95","electionPossibilityPercent":"44.0","possibilityChange":"0.49","possibilityChangePercent":"0.5","scores":{"achievement":"30.0","activity":"13.3","policy":"40.0","publicImage":"36.9","poll":"66.9"},"polls":{"count":7,"data":[{"pollAgency":"갤럽","surveyDate":"2026-01-20T00:00:00.000","surveyTimestamp":1768867200000,"supportRate":"65.0","sampleSize":1008,"marginOfError":"3.1"},{"pollAgency":"갤럽","surveyDate":"2026-01-28T00:00:00.000","surveyTimestamp":1769558400000,"supportRate":"67.0","sampleSize":1010,"marginOfError":"3.1"},{"pollAgency":"리서치앤리서치","surveyDate":"2026-01-25T00:00:00.000","surveyTimestamp":1769299200000,"supportRate":"63.0","sampleSize":1009,"marginOfError":"3.1"},{"pollAgency":"리서치앤리서치","surveyDate":"2026-02-01T00:00:00.000","surveyTimestamp":1769904000000,"supportRate":"68.0","sampleSize":1012,"marginOfError":"3.1"},{"pollAgency":"리얼미터","surveyDate":"2026-01-30T00:00:00.000","surveyTimestamp":1769731200000,"supportRate":"66.0","sampleSize":1000,"marginOfError":"3.1"},{"pollAgency":"리얼미터","surveyDate":"2026-02-03T00:00:00.000","surveyTimestamp":1770076800000,"supportRate":"69.0","sampleSize":1005,"marginOfError":"3.1"},{"pollAgency":"매일경제","surveyDate":"2026-02-02T00:00:00.000","surveyTimestamp":1769990400000,"supportRate":"70.0","sampleSize":1015,"marginOfError":"3.1"}]},"snsAnalysis":{"totalMentions":3,"sentiment":{"positive":2,"neutral":1,"negative":0},"sentimentScore":"76.7","topMentions":["정청래","대표가","더불어민주당","2026년","지방선거를"],"engagementTrend":"상승","sentimentRatio":{"positive":"66.7","neutral":"33.3","negative":"0.0"}},"pressReports":{"count":3,"sentimentAverage":"66.7"},"trends":{"recent":[{"date":"2026-03-01T17:35:14.095903","timestamp":1772386514095,"possibility":"44.9"},{"date":"2026-03-01T17:35:44.095903","timestamp":1772386544095,"possibility":"46.1"},{"date":"2026-03-01T17:36:14.095903","timestamp":1772386574095,"possibility":"46.3"},{"date":"2026-03-01T17:36:44.095903","timestamp":1772386604095,"possibility":"46.5"},{"date":"2026-03-01T17:37:14.095903","timestamp":1772386634095,"possibility":"46.4"},{"date":"2026-03-01T17:37:44.095903","timestamp":1772386664095,"possibility":"45.4"},{"date":"2026-03-01T17:38:14.095903","timestamp":1772386694095,"possibility":"45.1"},{"date":"2026-03-01T17:38:44.095903","timestamp":1772386724095,"possibility":"44.4"},{"date":"2026-03-01T17:39:14.095903","timestamp":1772386754095,"possibility":"43.9"},{"date":"2026-03-01T17:39:44.095903","timestamp":1772386784095,"possibility":"43.0"},{"date":"2026-03-01T17:40:14.095903","timestamp":1772386814095,"possibility":"44.0"},{"date":"2026-03-01T17:40:44.095903","timestamp":1772386844095,"possibility":"44.4"},{"date":"2026-03-01T17:41:14.095903","timestamp":1772386874095,"possibility":"44.2"},{"date":"2026-03-01T17:41:44.095903","timestamp":1772386904095,"possibility":"43.6"},{"date":"2026-03-01T17:42:14.095903","timestamp":1772386934095,"possibility":"42.2"},{"date":"2026-03-01T17:42:44.095903","timestamp":1772386964095,"possibility":"41.0"},{"date":"2026-03-01T17:43:14.095903","timestamp":1772386994095,"possibility":"41.0"},{"date":"2026-03-01T17:43:44.095903","timestamp":1772387024095,"possibility":"40.4"},{"date":"2026-03-01T17:44:14.095903","timestamp":1772387054095,"possibility":"40.7"},{"date":"2026-03-01T17:44:44.095903","timestamp":1772387084095,"possibility":"41.0"},{"date":"2026-03-01T17:45:14.095903","timestamp":1772387114095,"possibility":"42.5"},{"date":"2026-03-01T17:45:44.095903","timestamp":1772387144095,"possibility":"43.6"},{"date":"2026-03-01T17:46:14.095903","timestamp":1772387174095,"possibility":"44.0"},{"date":"2026-03-01T17:46:44.095903","timestamp":1772387204095,"possibility":"43.6"},{"date":"2026-03-01T17:47:14.095903","timestamp":1772387234095,"possibility":"42.9"},{"date":"2026-03-01T17:47:44.095903","timestamp":1772387264095,"possibility":"44.0"},{"date":"2026-03-01T17:48:14.095903","timestamp":1772387294095,"possibility":"45.2"},{"date":"2026-03-01T17:48:44.095903","timestamp":1772387324095,"possibility":"44.4"},{"date":"2026-03-01T17:49:14.095903","timestamp":1772387354095,"possibility":"43.5"},{"date":"2026-03-01T17:49:44.095903","timestamp":1772387384095,"possibility":"44.1"}],"count":30}},{"id":"member_002","name":"이준석","party":"국민의힘","district":"서울 강남구","timestamp":1772387384612,"analyzedAt":"2026-03-01T17:49:44.612747","electionPossibility":"41.37","electionPossibilityPercent":"41.4","possibilityChange":"-1.51","possibilityChangePercent":"-1.5","scores":{"achievement":"30.0","activity":"13.3","policy":"40.0","publicImage":"36.9","poll":"60.0"},"polls":{"count":3,"data":[{"pollAgency":"리서치앤리서치","surveyDate":"2026-01-22T00:00:00.000","surveyTimestamp":1769040000000,"supportRate":"58.0","sampleSize":1010,"marginOfError":"3.1"},{"pollAgency":"갤럽","surveyDate":"2026-01-29T00:00:00.000","surveyTimestamp":1769644800000,"supportRate":"60.0","sampleSize":1008,"marginOfError":"3.1"},{"pollAgency":"리얼미터","surveyDate":"2026-02-02T00:00:00.000","surveyTimestamp":1769990400000,"supportRate":"62.0","sampleSize":1005,"marginOfError":"3.1"}]},"snsAnalysis":{"totalMentions":3,"sentiment":{"positive":2,"neutral":1,"negative":0},"sentimentScore":"76.7","topMentions":["이준석이","2026년","서울시장","출마를","선언했다"],"engagementTrend":"상승","sentimentRatio":{"positive":"66.7","neutral":"33.3","negative":"0.0"}},"pressReports":{"count":3,"sentimentAverage":"66.7"},"trends":{"recent":[{"date":"2026-03-01T17:35:14.612041","timestamp":1772386514612,"possibility":"42.0"},{"date":"2026-03-01T17:35:44.612041","timestamp":1772386544612,"possibility":"42.1"},{"date":"2026-03-01T17:36:14.612041","timestamp":1772386574612,"possibility":"40.6"},{"date":"2026-03-01T17:36:44.612041","timestamp":1772386604612,"possibility":"40.9"},{"date":"2026-03-01T17:37:14.612041","timestamp":1772386634612,"possibility":"40.9"},{"date":"2026-03-01T17:37:44.612041","timestamp":1772386664612,"possibility":"41.4"},{"date":"2026-03-01T17:38:14.612041","timestamp":1772386694612,"possibility":"41.4"},{"date":"2026-03-01T17:38:44.612041","timestamp":1772386724612,"possibility":"40.5"},{"date":"2026-03-01T17:39:14.612041","timestamp":1772386754612,"possibility":"40.1"},{"date":"2026-03-01T17:39:44.612041","timestamp":1772386784612,"possibility":"41.4"},{"date":"2026-03-01T17:40:14.612041","timestamp":1772386814612,"possibility":"40.8"},{"date":"2026-03-01T17:40:44.612041","timestamp":1772386844612,"possibility":"40.5"},{"date":"2026-03-01T17:41:14.612041","timestamp":1772386874612,"possibility":"41.9"},{"date":"2026-03-01T17:41:44.612041","timestamp":1772386904612,"possibility":"41.2"},{"date":"2026-03-01T17:42:14.612041","timestamp":1772386934612,"possibility":"40.9"},{"date":"2026-03-01T17:42:44.612041","timestamp":1772386964612,"possibility":"40.5"},{"date":"2026-03-01T17:43:14.612041","timestamp":1772386994612,"possibility":"41.3"},{"date":"2026-03-01T17:43:44.612041","timestamp":1772387024612,"possibility":"41.7"},{"date":"2026-03-01T17:44:14.612041","timestamp":1772387054612,"possibility":"41.8"},{"date":"2026-03-01T17:44:44.612041","timestamp":1772387084612,"possibility":"42.8"},{"date":"2026-03-01T17:45:14.612041","timestamp":1772387114612,"possibility":"43.0"},{"date":"2026-03-01T17:45:44.612041","timestamp":1772387144612,"possibility":"43.2"},{"date":"2026-03-01T17:46:14.612041","timestamp":1772387174612,"possibility":"41.9"},{"date":"2026-03-01T17:46:44.612041","timestamp":1772387204612,"possibility":"40.7"},{"date":"2026-03-01T17:47:14.612041","timestamp":1772387234612,"possibility":"41.6"},{"date":"2026-03-01T17:47:44.612041","timestamp":1772387264612,"possibility":"41.2"},{"date":"2026-03-01T17:48:14.612041","timestamp":1772387294612,"possibility":"39.9"},{"date":"2026-03-01T17:48:44.612041","timestamp":1772387324612,"possibility":"41.6"},{"date":"2026-03-01T17:49:14.612041","timestamp":1772387354612,"possibility":"42.9"},{"date":"2026-03-01T17:49:44.612041","timestamp":1772387384612,"possibility":"41.8"}],"count":30}},{"id":"member_003","name":"박형준","party":"국민의힘","district":"부산광역시","timestamp":1772387385114,"analyzedAt":"2026-03-01T17:49:45.114848","electionPossibility":"49.29","electionPossibilityPercent":"49.3","possibilityChange":"-0.77","possibilityChangePercent":"-0.8","scores":{"achievement":"30.0","activity":"13.3","policy":"40.0","publicImage":"36.9","poll":"72.0"},"polls":{"count":3,"data":[{"pollAgency":"갤럽","surveyDate":"2026-01-21T00:00:00.000","surveyTimestamp":1768953600000,"supportRate":"72.0","sampleSize":1010,"marginOfError":"3.1"},{"pollAgency":"리서치앤리서치","surveyDate":"2026-01-27T00:00:00.000","surveyTimestamp":1769472000000,"supportRate":"70.0","sampleSize":1009,"marginOfError":"3.1"},{"pollAgency":"리얼미터","surveyDate":"2026-02-03T00:00:00.000","surveyTimestamp":1770076800000,"supportRate":"74.0","sampleSize":1008,"marginOfError":"3.1"}]},"snsAnalysis":{"totalMentions":3,"sentiment":{"positive":2,"neutral":1,"negative":0},"sentimentScore":"76.7","topMentions":["박형준이","부산광역시장","의사를","표현했다","박형준"],"engagementTrend":"상승","sentimentRatio":{"positive":"66.7","neutral":"33.3","negative":"0.0"}},"pressReports":{"count":3,"sentimentAverage":"66.7"},"trends":{"recent":[{"date":"2026-03-01T17:35:15.114009","timestamp":1772386515114,"possibility":"46.8"},{"date":"2026-03-01T17:35:45.114009","timestamp":1772386545114,"possibility":"46.0"},{"date":"2026-03-01T17:36:15.114009","timestamp":1772386575114,"possibility":"46.5"},{"date":"2026-03-01T17:36:45.114009","timestamp":1772386605114,"possibility":"46.1"},{"date":"2026-03-01T17:37:15.114009","timestamp":1772386635114,"possibility":"46.5"},{"date":"2026-03-01T17:37:45.114009","timestamp":1772386665114,"possibility":"46.9"},{"date":"2026-03-01T17:38:15.114009","timestamp":1772386695114,"possibility":"47.3"},{"date":"2026-03-01T17:38:45.114009","timestamp":1772386725114,"possibility":"47.3"},{"date":"2026-03-01T17:39:15.114009","timestamp":1772386755114,"possibility":"47.2"},{"date":"2026-03-01T17:39:45.114009","timestamp":1772386785114,"possibility":"45.9"},{"date":"2026-03-01T17:40:15.114009","timestamp":1772386815114,"possibility":"46.9"},{"date":"2026-03-01T17:40:45.114009","timestamp":1772386845114,"possibility":"47.8"},{"date":"2026-03-01T17:41:15.114009","timestamp":1772386875114,"possibility":"47.9"},{"date":"2026-03-01T17:41:45.114009","timestamp":1772386905114,"possibility":"47.4"},{"date":"2026-03-01T17:42:15.114009","timestamp":1772386935114,"possibility":"47.5"},{"date":"2026-03-01T17:42:45.114009","timestamp":1772386965114,"possibility":"48.2"},{"date":"2026-03-01T17:43:15.114009","timestamp":1772386995114,"possibility":"48.9"},{"date":"2026-03-01T17:43:45.114009","timestamp":1772387025114,"possibility":"47.3"},{"date":"2026-03-01T17:44:15.114009","timestamp":1772387055114,"possibility":"46.8"},{"date":"2026-03-01T17:44:45.114009","timestamp":1772387085114,"possibility":"46.8"},{"date":"2026-03-01T17:45:15.114009","timestamp":1772387115114,"possibility":"46.7"},{"date":"2026-03-01T17:45:45.114009","timestamp":1772387145114,"possibility":"47.4"},{"date":"2026-03-01T17:46:15.114009","timestamp":1772387175114,"possibility":"48.3"},{"date":"2026-03-01T17:46:45.114009","timestamp":1772387205114,"possibility":"49.5"},{"date":"2026-03-01T17:47:15.114009","timestamp":1772387235114,"possibility":"48.2"},{"date":"2026-03-01T17:47:45.114009","timestamp":1772387265114,"possibility":"48.0"},{"date":"2026-03-01T17:48:15.114009","timestamp":1772387295114,"possibility":"48.8"},{"date":"2026-03-01T17:48:45.114009","timestamp":1772387325114,"possibility":"49.6"},{"date":"2026-03-01T17:49:15.114009","timestamp":1772387355114,"possibility":"50.1"},{"date":"2026-03-01T17:49:45.114009","timestamp":1772387385114,"possibility":"50.9"}],"count":30}},{"id":"member_004","name":"강선우","party":"국민의힘","district":"인천광역시","timestamp":1772387385616,"analyzedAt":"2026-03-01T17:49:45.616847","electionPossibility":"28.38","electionPossibilityPercent":"28.4","possibilityChange":"1.39","possibilityChangePercent":"1.4","scores":{"achievement":"30.0","activity":"13.3","policy":"40.0","publicImage":"24.8","poll":"32.2"},"polls":{"count":1,"data":[{"pollAgency":"조원씨앤아이","surveyDate":"2025-07-21T00:00:00.000","surveyTimestamp":1753056000000,"supportRate":"32.2","sampleSize":2002,"marginOfError":"2.2"}]},"snsAnalysis":{"totalMentions":4,"sentiment":{"positive":2,"neutral":1,"negative":1},"sentimentScore":"32.5","topMentions":["강선우가","인천시장","선거에","국민의힘","후보로"],"engagementTrend":"하락","sentimentRatio":{"positive":"50.0","neutral":"25.0","negative":"25.0"}},"pressReports":{"count":4,"sentimentAverage":"50.0"},"trends":{"recent":[{"date":"2026-03-01T17:35:15.616013","timestamp":1772386515616,"possibility":"29.1"},{"date":"2026-03-01T17:35:45.616013","timestamp":1772386545616,"possibility":"28.9"},{"date":"2026-03-01T17:36:15.616013","timestamp":1772386575616,"possibility":"28.6"},{"date":"2026-03-01T17:36:45.616013","timestamp":1772386605616,"possibility":"28.9"},{"date":"2026-03-01T17:37:15.616013","timestamp":1772386635616,"possibility":"30.3"},{"date":"2026-03-01T17:37:45.616013","timestamp":1772386665616,"possibility":"30.4"},{"date":"2026-03-01T17:38:15.616013","timestamp":1772386695616,"possibility":"29.1"},{"date":"2026-03-01T17:38:45.616013","timestamp":1772386725616,"possibility":"30.3"},{"date":"2026-03-01T17:39:15.616013","timestamp":1772386755616,"possibility":"29.3"},{"date":"2026-03-01T17:39:45.616013","timestamp":1772386785616,"possibility":"27.8"},{"date":"2026-03-01T17:40:15.616013","timestamp":1772386815616,"possibility":"27.3"},{"date":"2026-03-01T17:40:45.616013","timestamp":1772386845616,"possibility":"27.6"},{"date":"2026-03-01T17:41:15.616013","timestamp":1772386875616,"possibility":"28.8"},{"date":"2026-03-01T17:41:45.616013","timestamp":1772386905616,"possibility":"27.5"},{"date":"2026-03-01T17:42:15.616013","timestamp":1772386935616,"possibility":"27.7"},{"date":"2026-03-01T17:42:45.616013","timestamp":1772386965616,"possibility":"29.3"},{"date":"2026-03-01T17:43:15.616013","timestamp":1772386995616,"possibility":"30.3"},{"date":"2026-03-01T17:43:45.616013","timestamp":1772387025616,"possibility":"31.5"},{"date":"2026-03-01T17:44:15.616013","timestamp":1772387055616,"possibility":"31.2"},{"date":"2026-03-01T17:44:45.616013","timestamp":1772387085616,"possibility":"30.0"},{"date":"2026-03-01T17:45:15.616013","timestamp":1772387115616,"possibility":"28.9"},{"date":"2026-03-01T17:45:45.616013","timestamp":1772387145616,"possibility":"27.7"},{"date":"2026-03-01T17:46:15.616013","timestamp":1772387175616,"possibility":"29.1"},{"date":"2026-03-01T17:46:45.616013","timestamp":1772387205616,"possibility":"28.9"},{"date":"2026-03-01T17:47:15.616013","timestamp":1772387235616,"possibility":"29.7"},{"date":"2026-03-01T17:47:45.616013","timestamp":1772387265616,"possibility":"29.8"},{"date":"2026-03-01T17:48:15.616013","timestamp":1772387295616,"possibility":"29.1"},{"date":"2026-03-01T17:48:45.616013","timestamp":1772387325616,"possibility":"27.9"},{"date":"2026-03-01T17:49:15.616013","timestamp":1772387355616,"possibility":"27.0"},{"date":"2026-03-01T17:49:45.616013","timestamp":1772387385616,"possibility":"26.3"}],"count":30}},{"id":"member_005","name":"신상진","party":"더불어민주당","district":"대전광역시","timestamp":1772387386119,"analyzedAt":"2026-03-01T17:49:46.119232","electionPossibility":"42.86","electionPossibilityPercent":"42.9","possibilityChange":"-0.62","possibilityChangePercent":"-0.6","scores":{"achievement":"30.0","activity":"13.3","policy":"40.0","publicImage":"36.9","poll":"61.0"},"polls":{"count":3,"data":[{"pollAgency":"갤럽","surveyDate":"2026-01-23T00:00:00.000","surveyTimestamp":1769126400000,"supportRate":"61.0","sampleSize":1009,"marginOfError":"3.1"},{"pollAgency":"리서치앤리서치","surveyDate":"2026-01-29T00:00:00.000","surveyTimestamp":1769644800000,"supportRate":"59.0","sampleSize":1011,"marginOfError":"3.1"},{"pollAgency":"리얼미터","surveyDate":"2026-02-03T00:00:00.000","surveyTimestamp":1770076800000,"supportRate":"63.0","sampleSize":1006,"marginOfError":"3.1"}]},"snsAnalysis":{"totalMentions":3,"sentiment":{"positive":2,"neutral":1,"negative":0},"sentimentScore":"76.7","topMentions":["중소기업","신상진이","더불어민주당","후보로서","대전시장"],"engagementTrend":"상승","sentimentRatio":{"positive":"66.7","neutral":"33.3","negative":"0.0"}},"pressReports":{"count":3,"sentimentAverage":"66.7"},"trends":{"recent":[{"date":"2026-03-01T17:35:16.117986","timestamp":1772386516117,"possibility":"42.4"},{"date":"2026-03-01T17:35:46.117986","timestamp":1772386546117,"possibility":"41.5"},{"date":"2026-03-01T17:36:16.117986","timestamp":1772386576117,"possibility":"40.3"},{"date":"2026-03-01T17:36:46.117986","timestamp":1772386606117,"possibility":"40.5"},{"date":"2026-03-01T17:37:16.117986","timestamp":1772386636117,"possibility":"41.4"},{"date":"2026-03-01T17:37:46.117986","timestamp":1772386666117,"possibility":"42.5"},{"date":"2026-03-01T17:38:16.117986","timestamp":1772386696117,"possibility":"43.4"},{"date":"2026-03-01T17:38:46.117986","timestamp":1772386726117,"possibility":"44.5"},{"date":"2026-03-01T17:39:16.117986","timestamp":1772386756117,"possibility":"45.1"},{"date":"2026-03-01T17:39:46.117986","timestamp":1772386786117,"possibility":"45.0"},{"date":"2026-03-01T17:40:16.117986","timestamp":1772386816117,"possibility":"44.9"},{"date":"2026-03-01T17:40:46.117986","timestamp":1772386846117,"possibility":"46.1"},{"date":"2026-03-01T17:41:16.117986","timestamp":1772386876117,"possibility":"46.7"},{"date":"2026-03-01T17:41:46.117986","timestamp":1772386906117,"possibility":"45.4"},{"date":"2026-03-01T17:42:16.117986","timestamp":1772386936117,"possibility":"46.2"},{"date":"2026-03-01T17:42:46.117986","timestamp":1772386966117,"possibility":"45.9"},{"date":"2026-03-01T17:43:16.117986","timestamp":1772386996117,"possibility":"46.1"},{"date":"2026-03-01T17:43:46.117986","timestamp":1772387026117,"possibility":"44.8"},{"date":"2026-03-01T17:44:16.117986","timestamp":1772387056117,"possibility":"43.6"},{"date":"2026-03-01T17:44:46.117986","timestamp":1772387086117,"possibility":"44.2"},{"date":"2026-03-01T17:45:16.117986","timestamp":1772387116117,"possibility":"43.3"},{"date":"2026-03-01T17:45:46.117986","timestamp":1772387146117,"possibility":"42.0"},{"date":"2026-03-01T17:46:16.117986","timestamp":1772387176117,"possibility":"43.1"},{"date":"2026-03-01T17:46:46.117986","timestamp":1772387206117,"possibility":"41.8"},{"date":"2026-03-01T17:47:16.117986","timestamp":1772387236117,"possibility":"41.0"},{"date":"2026-03-01T17:47:46.117986","timestamp":1772387266117,"possibility":"42.6"},{"date":"2026-03-01T17:48:16.117986","timestamp":1772387296117,"possibility":"44.0"},{"date":"2026-03-01T17:48:46.117986","timestamp":1772387326117,"possibility":"43.0"},{"date":"2026-03-01T17:49:16.117986","timestamp":1772387356117,"possibility":"43.5"},{"date":"2026-03-01T17:49:46.117986","timestamp":1772387386117,"possibility":"44.1"}],"count":30}},{"id":"member_006","name":"서영교","party":"더불어민주당","district":"서울특별시장","timestamp":1772387386620,"analyzedAt":"2026-03-01T17:49:46.620856","electionPossibility":"25.86","electionPossibilityPercent":"25.9","possibilityChange":"0.71","possibilityChangePercent":"0.7","scores":{"achievement":"5.0","activity":"3.3","policy":"0.0","publicImage":"21.2","poll":"50.0"},"polls":{"count":0,"data":[]},"snsAnalysis":{"totalMentions":1,"sentiment":{"positive":0,"neutral":1,"negative":0},"sentimentScore":"30.0","topMentions":["서영교","의원이","2026년","서울시장","출마를"],"engagementTrend":"하락","sentimentRatio":{"positive":"0.0","neutral":"100.0","negative":"0.0"}},"pressReports":{"count":1,"sentimentAverage":"0.0"},"trends":{"recent":[{"date":"2026-03-01T17:35:16.620190","timestamp":1772386516620,"possibility":"24.4"},{"date":"2026-03-01T17:35:46.620190","timestamp":1772386546620,"possibility":"25.6"},{"date":"2026-03-01T17:36:16.620190","timestamp":1772386576620,"possibility":"24.9"},{"date":"2026-03-01T17:36:46.620190","timestamp":1772386606620,"possibility":"24.5"},{"date":"2026-03-01T17:37:16.620190","timestamp":1772386636620,"possibility":"24.5"},{"date":"2026-03-01T17:37:46.620190","timestamp":1772386666620,"possibility":"25.8"},{"date":"2026-03-01T17:38:16.620190","timestamp":1772386696620,"possibility":"25.3"},{"date":"2026-03-01T17:38:46.620190","timestamp":1772386726620,"possibility":"24.1"},{"date":"2026-03-01T17:39:16.620190","timestamp":1772386756620,"possibility":"22.7"},{"date":"2026-03-01T17:39:46.620190","timestamp":1772386786620,"possibility":"22.0"},{"date":"2026-03-01T17:40:16.620190","timestamp":1772386816620,"possibility":"21.2"},{"date":"2026-03-01T17:40:46.620190","timestamp":1772386846620,"possibility":"21.1"},{"date":"2026-03-01T17:41:16.620190","timestamp":1772386876620,"possibility":"20.1"},{"date":"2026-03-01T17:41:46.620190","timestamp":1772386906620,"possibility":"21.8"},{"date":"2026-03-01T17:42:16.620190","timestamp":1772386936620,"possibility":"22.3"},{"date":"2026-03-01T17:42:46.620190","timestamp":1772386966620,"possibility":"21.1"},{"date":"2026-03-01T17:43:16.620190","timestamp":1772386996620,"possibility":"20.2"},{"date":"2026-03-01T17:43:46.620190","timestamp":1772387026620,"possibility":"21.6"},{"date":"2026-03-01T17:44:16.620190","timestamp":1772387056620,"possibility":"22.4"},{"date":"2026-03-01T17:44:46.620190","timestamp":1772387086620,"possibility":"22.7"},{"date":"2026-03-01T17:45:16.620190","timestamp":1772387116620,"possibility":"23.4"},{"date":"2026-03-01T17:45:46.620190","timestamp":1772387146620,"possibility":"24.7"},{"date":"2026-03-01T17:46:16.620190","timestamp":1772387176620,"possibility":"25.0"},{"date":"2026-03-01T17:46:46.620190","timestamp":1772387206620,"possibility":"26.4"},{"date":"2026-03-01T17:47:16.620190","timestamp":1772387236620,"possibility":"27.0"},{"date":"2026-03-01T17:47:46.620190","timestamp":1772387266620,"possibility":"26.5"},{"date":"2026-03-01T17:48:16.620190","timestamp":1772387296620,"possibility":"26.2"},{"date":"2026-03-01T17:48:46.620190","timestamp":1772387326620,"possibility":"25.9"},{"date":"2026-03-01T17:49:16.620190","timestamp":1772387356620,"possibility":"25.2"},{"date":"2026-03-01T17:49:46.620190","timestamp":1772387386620,"possibility":"23.9"}],"count":30}},{"id":"member_007","name":"김교흥","party":"더불어민주당","district":"인천광역시장","timestamp":1772387387122,"analyzedAt":"2026-03-01T17:49:47.122476","electionPossibility":"29.43","electionPossibilityPercent":"29.4","possibilityChange":"-1.76","possibilityChangePercent":"-1.8","scores":{"achievement":"5.0","activity":"3.3","policy":"0.0","publicImage":"21.2","poll":"50.0"},"polls":{"count":0,"data":[]},"snsAnalysis":{"totalMentions":1,"sentiment":{"positive":0,"neutral":1,"negative":0},"sentimentScore":"30.0","topMentions":["김교흥","의원이","2026년","인천시장","출마를"],"engagementTrend":"하락","sentimentRatio":{"positive":"0.0","neutral":"100.0","negative":"0.0"}},"pressReports":{"count":1,"sentimentAverage":"0.0"},"trends":{"recent":[{"date":"2026-03-01T17:35:17.121933","timestamp":1772386517121,"possibility":"24.4"},{"date":"2026-03-01T17:35:47.121933","timestamp":1772386547121,"possibility":"25.7"},{"date":"2026-03-01T17:36:17.121933","timestamp":1772386577121,"possibility":"26.7"},{"date":"2026-03-01T17:36:47.121933","timestamp":1772386607121,"possibility":"26.5"},{"date":"2026-03-01T17:37:17.121933","timestamp":1772386637121,"possibility":"25.6"},{"date":"2026-03-01T17:37:47.121933","timestamp":1772386667121,"possibility":"26.6"},{"date":"2026-03-01T17:38:17.121933","timestamp":1772386697121,"possibility":"26.2"},{"date":"2026-03-01T17:38:47.121933","timestamp":1772386727121,"possibility":"24.6"},{"date":"2026-03-01T17:39:17.121933","timestamp":1772386757121,"possibility":"25.5"},{"date":"2026-03-01T17:39:47.121933","timestamp":1772386787121,"possibility":"26.9"},{"date":"2026-03-01T17:40:17.121933","timestamp":1772386817121,"possibility":"25.5"},{"date":"2026-03-01T17:40:47.121933","timestamp":1772386847121,"possibility":"25.5"},{"date":"2026-03-01T17:41:17.121933","timestamp":1772386877121,"possibility":"25.6"},{"date":"2026-03-01T17:41:47.121933","timestamp":1772386907121,"possibility":"25.9"},{"date":"2026-03-01T17:42:17.121933","timestamp":1772386937121,"possibility":"26.8"},{"date":"2026-03-01T17:42:47.121933","timestamp":1772386967121,"possibility":"28.1"},{"date":"2026-03-01T17:43:17.121933","timestamp":1772386997121,"possibility":"26.4"},{"date":"2026-03-01T17:43:47.121933","timestamp":1772387027121,"possibility":"27.1"},{"date":"2026-03-01T17:44:17.121933","timestamp":1772387057121,"possibility":"26.4"},{"date":"2026-03-01T17:44:47.121933","timestamp":1772387087121,"possibility":"27.0"},{"date":"2026-03-01T17:45:17.121933","timestamp":1772387117121,"possibility":"27.3"},{"date":"2026-03-01T17:45:47.121933","timestamp":1772387147121,"possibility":"28.1"},{"date":"2026-03-01T17:46:17.121933","timestamp":1772387177121,"possibility":"28.0"},{"date":"2026-03-01T17:46:47.121933","timestamp":1772387207121,"possibility":"27.1"},{"date":"2026-03-01T17:47:17.121933","timestamp":1772387237121,"possibility":"28.2"},{"date":"2026-03-01T17:47:47.121933","timestamp":1772387267121,"possibility":"29.2"},{"date":"2026-03-01T17:48:17.121933","timestamp":1772387297121,"possibility":"29.8"},{"date":"2026-03-01T17:48:47.121933","timestamp":1772387327121,"possibility":"30.3"},{"date":"2026-03-01T17:49:17.121933","timestamp":1772387357121,"possibility":"31.2"},{"date":"2026-03-01T17:49:47.121933","timestamp":1772387387121,"possibility":"30.2"}],"count":30}},{"id":"member_008","name":"전현희","party":"더불어민주당","district":"서울특별시장","timestamp":1772387387623,"analyzedAt":"2026-03-01T17:49:47.623305","electionPossibility":"21.93","electionPossibilityPercent":"21.9","possibilityChange":"-0.65","possibilityChangePercent":"-0.6","scores":{"achievement":"5.0","activity":"3.3","policy":"0.0","publicImage":"21.2","poll":"50.0"},"polls":{"count":0,"data":[]},"snsAnalysis":{"totalMentions":1,"sentiment":{"positive":0,"neutral":1,"negative":0},"sentimentScore":"30.0","topMentions":["전현희","의원이","2026년","서울시장","출마를"],"engagementTrend":"하락","sentimentRatio":{"positive":"0.0","neutral":"100.0","negative":"0.0"}},"pressReports":{"count":1,"sentimentAverage":"0.0"},"trends":{"recent":[{"date":"2026-03-01T17:35:17.622871","timestamp":1772386517622,"possibility":"24.4"},{"date":"2026-03-01T17:35:47.622871","timestamp":1772386547622,"possibility":"25.2"},{"date":"2026-03-01T17:36:17.622871","timestamp":1772386577622,"possibility":"24.6"},{"date":"2026-03-01T17:36:47.622871","timestamp":1772386607622,"possibility":"24.7"},{"date":"2026-03-01T17:37:17.622871","timestamp":1772386637622,"possibility":"24.2"},{"date":"2026-03-01T17:37:47.622871","timestamp":1772386667622,"possibility":"25.0"},{"date":"2026-03-01T17:38:17.622871","timestamp":1772386697622,"possibility":"25.7"},{"date":"2026-03-01T17:38:47.622871","timestamp":1772386727622,"possibility":"26.8"},{"date":"2026-03-01T17:39:17.622871","timestamp":1772386757622,"possibility":"27.5"},{"date":"2026-03-01T17:39:47.622871","timestamp":1772386787622,"possibility":"28.3"},{"date":"2026-03-01T17:40:17.622871","timestamp":1772386817622,"possibility":"26.8"},{"date":"2026-03-01T17:40:47.622871","timestamp":1772386847622,"possibility":"26.2"},{"date":"2026-03-01T17:41:17.622871","timestamp":1772386877622,"possibility":"25.6"},{"date":"2026-03-01T17:41:47.622871","timestamp":1772386907622,"possibility":"25.3"},{"date":"2026-03-01T17:42:17.622871","timestamp":1772386937622,"possibility":"24.7"},{"date":"2026-03-01T17:42:47.622871","timestamp":1772386967622,"possibility":"25.9"},{"date":"2026-03-01T17:43:17.622871","timestamp":1772386997622,"possibility":"24.7"},{"date":"2026-03-01T17:43:47.622871","timestamp":1772387027622,"possibility":"25.7"},{"date":"2026-03-01T17:44:17.622871","timestamp":1772387057622,"possibility":"25.0"},{"date":"2026-03-01T17:44:47.622871","timestamp":1772387087622,"possibility":"24.3"},{"date":"2026-03-01T17:45:17.622871","timestamp":1772387117622,"possibility":"23.0"},{"date":"2026-03-01T17:45:47.622871","timestamp":1772387147622,"possibility":"21.7"},{"date":"2026-03-01T17:46:17.622871","timestamp":1772387177622,"possibility":"21.5"},{"date":"2026-03-01T17:46:47.622871","timestamp":1772387207622,"possibility":"22.3"},{"date":"2026-03-01T17:47:17.622871","timestamp":1772387237622,"possibility":"21.5"},{"date":"2026-03-01T17:47:47.622871","timestamp":1772387267622,"possibility":"20.6"},{"date":"2026-03-01T17:48:17.622871","timestamp":1772387297622,"possibility":"21.4"},{"date":"2026-03-01T17:48:47.622871","timestamp":1772387327622,"possibility":"22.9"},{"date":"2026-03-01T17:49:17.622871","timestamp":1772387357622,"possibility":"22.6"},{"date":"2026-03-01T17:49:47.622871","timestamp":1772387387622,"possibility":"22.3"}],"count":30}},{"id":"member_009","name":"박주민","party":"더불어민주당","district":"서울특별시장","timestamp":1772387388124,"analyzedAt":"2026-03-01T17:49:48.124515","electionPossibility":"20.78","electionPossibilityPercent":"20.8","possibilityChange":"-0.86","possibilityChangePercent":"-0.9","scores":{"achievement":"5.0","activity":"3.3","policy":"0.0","publicImage":"21.2","poll":"50.0"},"polls":{"count":0,"data":[]},"snsAnalysis":{"totalMentions":1,"sentiment":{"positive":0,"neutral":1,"negative":0},"sentimentScore":"30.0","topMentions":["박주민","의원이","2026년","서울시장","출마를"],"engagementTrend":"하락","sentimentRatio":{"positive":"0.0","neutral":"100.0","negative":"0.0"}},"pressReports":{"count":1,"sentimentAverage":"0.0"},"trends":{"recent":[{"date":"2026-03-01T17:35:18.123958","timestamp":1772386518123,"possibility":"24.4"},{"date":"2026-03-01T17:35:48.123958","timestamp":1772386548123,"possibility":"23.3"},{"date":"2026-03-01T17:36:18.123958","timestamp":1772386578123,"possibility":"22.6"},{"date":"2026-03-01T17:36:48.123958","timestamp":1772386608123,"possibility":"22.0"},{"date":"2026-03-01T17:37:18.123958","timestamp":1772386638123,"possibility":"20.8"},{"date":"2026-03-01T17:37:48.123958","timestamp":1772386668123,"possibility":"20.9"},{"date":"2026-03-01T17:38:18.123958","timestamp":1772386698123,"possibility":"20.2"},{"date":"2026-03-01T17:38:48.123958","timestamp":1772386728123,"possibility":"20.0"},{"date":"2026-03-01T17:39:18.123958","timestamp":1772386758123,"possibility":"20.0"},{"date":"2026-03-01T17:39:48.123958","timestamp":1772386788123,"possibility":"20.0"},{"date":"2026-03-01T17:40:18.123958","timestamp":1772386818123,"possibility":"20.7"},{"date":"2026-03-01T17:40:48.123958","timestamp":1772386848123,"possibility":"20.0"},{"date":"2026-03-01T17:41:18.123958","timestamp":1772386878123,"possibility":"20.0"},{"date":"2026-03-01T17:41:48.123958","timestamp":1772386908123,"possibility":"21.5"},{"date":"2026-03-01T17:42:18.123958","timestamp":1772386938123,"possibility":"22.0"},{"date":"2026-03-01T17:42:48.123958","timestamp":1772386968123,"possibility":"22.5"},{"date":"2026-03-01T17:43:18.123958","timestamp":1772386998123,"possibility":"22.1"},{"date":"2026-03-01T17:43:48.123958","timestamp":1772387028123,"possibility":"21.8"},{"date":"2026-03-01T17:44:18.123958","timestamp":1772387058123,"possibility":"21.0"},{"date":"2026-03-01T17:44:48.123958","timestamp":1772387088123,"possibility":"21.3"},{"date":"2026-03-01T17:45:18.123958","timestamp":1772387118123,"possibility":"21.7"},{"date":"2026-03-01T17:45:48.123958","timestamp":1772387148123,"possibility":"21.1"},{"date":"2026-03-01T17:46:18.123958","timestamp":1772387178123,"possibility":"22.1"},{"date":"2026-03-01T17:46:48.123958","timestamp":1772387208123,"possibility":"21.0"},{"date":"2026-03-01T17:47:18.123958","timestamp":1772387238123,"possibility":"20.9"},{"date":"2026-03-01T17:47:48.123958","timestamp":1772387268123,"possibility":"20.9"},{"date":"2026-03-01T17:48:18.123958","timestamp":1772387298123,"possibility":"20.6"},{"date":"2026-03-01T17:48:48.123958","timestamp":1772387328123,"possibility":"20.0"},{"date":"2026-03-01T17:49:18.123958","timestamp":1772387358123,"possibility":"21.6"},{"date":"2026-03-01T17:49:48.123958","timestamp":1772387388123,"possibility":"20.4"}],"count":30}},{"id":"member_010","name":"권칠승","party":"더불어민주당","district":"경기도지사","timestamp":1772387388625,"analyzedAt":"2026-03-01T17:49:48.625455","electionPossibility":"21.27","electionPossibilityPercent":"21.3","possibilityChange":"-1.27","possibilityChangePercent":"-1.3","scores":{"achievement":"5.0","activity":"3.3","policy":"0.0","publicImage":"21.2","poll":"50.0"},"polls":{"count":0,"data":[]},"snsAnalysis":{"totalMentions":1,"sentiment":{"positive":0,"neutral":1,"negative":0},"sentimentScore":"30.0","topMentions":["권칠승","의원이","2026년","경기도지사","출마를"],"engagementTrend":"하락","sentimentRatio":{"positive":"0.0","neutral":"100.0","negative":"0.0"}},"pressReports":{"count":1,"sentimentAverage":"0.0"},"trends":{"recent":[{"date":"2026-03-01T17:35:18.624916","timestamp":1772386518624,"possibility":"24.4"},{"date":"2026-03-01T17:35:48.624916","timestamp":1772386548624,"possibility":"24.5"},{"date":"2026-03-01T17:36:18.624916","timestamp":1772386578624,"possibility":"24.1"},{"date":"2026-03-01T17:36:48.624916","timestamp":1772386608624,"possibility":"24.8"},{"date":"2026-03-01T17:37:18.624916","timestamp":1772386638624,"possibility":"23.5"},{"date":"2026-03-01T17:37:48.624916","timestamp":1772386668624,"possibility":"22.6"},{"date":"2026-03-01T17:38:18.624916","timestamp":1772386698624,"possibility":"22.9"},{"date":"2026-03-01T17:38:48.624916","timestamp":1772386728624,"possibility":"21.9"},{"date":"2026-03-01T17:39:18.624916","timestamp":1772386758624,"possibility":"21.0"},{"date":"2026-03-01T17:39:48.624916","timestamp":1772386788624,"possibility":"21.2"},{"date":"2026-03-01T17:40:18.624916","timestamp":1772386818624,"possibility":"20.3"},{"date":"2026-03-01T17:40:48.624916","timestamp":1772386848624,"possibility":"20.8"},{"date":"2026-03-01T17:41:18.624916","timestamp":1772386878624,"possibility":"21.3"},{"date":"2026-03-01T17:41:48.624916","timestamp":1772386908624,"possibility":"20.2"},{"date":"2026-03-01T17:42:18.624916","timestamp":1772386938624,"possibility":"20.0"},{"date":"2026-03-01T17:42:48.624916","timestamp":1772386968624,"possibility":"20.4"},{"date":"2026-03-01T17:43:18.624916","timestamp":1772386998624,"possibility":"21.0"},{"date":"2026-03-01T17:43:48.624916","timestamp":1772387028624,"possibility":"22.2"},{"date":"2026-03-01T17:44:18.624916","timestamp":1772387058624,"possibility":"23.1"},{"date":"2026-03-01T17:44:48.624916","timestamp":1772387088624,"possibility":"24.0"},{"date":"2026-03-01T17:45:18.624916","timestamp":1772387118624,"possibility":"24.1"},{"date":"2026-03-01T17:45:48.624916","timestamp":1772387148624,"possibility":"22.9"},{"date":"2026-03-01T17:46:18.624916","timestamp":1772387178624,"possibility":"22.0"},{"date":"2026-03-01T17:46:48.624916","timestamp":1772387208624,"possibility":"20.8"},{"date":"2026-03-01T17:47:18.624916","timestamp":1772387238624,"possibility":"20.0"},{"date":"2026-03-01T17:47:48.624916","timestamp":1772387268624,"possibility":"20.0"},{"date":"2026-03-01T17:48:18.624916","timestamp":1772387298624,"possibility":"21.1"},{"date":"2026-03-01T17:48:48.624916","timestamp":1772387328624,"possibility":"22.8"},{"date":"2026-03-01T17:49:18.624916","timestamp":1772387358624,"possibility":"22.5"},{"date":"2026-03-01T17:49:48.624916","timestamp":1772387388624,"possibility":"21.7"}],"count":30}},{"id":"member_011","name":"김병주","party":"더불어민주당","district":"경기도지사","timestamp":1772387389126,"analyzedAt":"2026-03-01T17:49:49.126481","electionPossibility":"23.81","electionPossibilityPercent":"23.8","possibilityChange":"-0.14","possibilityChangePercent":"-0.1","scores":{"achievement":"5.0","activity":"3.3","policy":"0.0","publicImage":"21.2","poll":"50.0"},"polls":{"count":0,"data":[]},"snsAnalysis":{"totalMentions":1,"sentiment":{"positive":0,"neutral":1,"negative":0},"sentimentScore":"30.0","topMentions":["김병주","의원이","2026년","경기도지사","출마를"],"engagementTrend":"하락","sentimentRatio":{"positive":"0.0","neutral":"100.0","negative":"0.0"}},"pressReports":{"count":1,"sentimentAverage":"0.0"},"trends":{"recent":[{"date":"2026-03-01T17:35:19.125950","timestamp":1772386519125,"possibility":"24.4"},{"date":"2026-03-01T17:35:49.125950","timestamp":1772386549125,"possibility":"24.2"},{"date":"2026-03-01T17:36:19.125950","timestamp":1772386579125,"possibility":"24.3"},{"date":"2026-03-01T17:36:49.125950","timestamp":1772386609125,"possibility":"23.3"},{"date":"2026-03-01T17:37:19.125950","timestamp":1772386639125,"possibility":"23.4"},{"date":"2026-03-01T17:37:49.125950","timestamp":1772386669125,"possibility":"24.2"},{"date":"2026-03-01T17:38:19.125950","timestamp":1772386699125,"possibility":"25.1"},{"date":"2026-03-01T17:38:49.125950","timestamp":1772386729125,"possibility":"23.7"},{"date":"2026-03-01T17:39:19.125950","timestamp":1772386759125,"possibility":"24.8"},{"date":"2026-03-01T17:39:49.125950","timestamp":1772386789125,"possibility":"23.5"},{"date":"2026-03-01T17:40:19.125950","timestamp":1772386819125,"possibility":"23.3"},{"date":"2026-03-01T17:40:49.125950","timestamp":1772386849125,"possibility":"24.8"},{"date":"2026-03-01T17:41:19.125950","timestamp":1772386879125,"possibility":"23.9"},{"date":"2026-03-01T17:41:49.125950","timestamp":1772386909125,"possibility":"25.1"},{"date":"2026-03-01T17:42:19.125950","timestamp":1772386939125,"possibility":"25.8"},{"date":"2026-03-01T17:42:49.125950","timestamp":1772386969125,"possibility":"25.8"},{"date":"2026-03-01T17:43:19.125950","timestamp":1772386999125,"possibility":"26.1"},{"date":"2026-03-01T17:43:49.125950","timestamp":1772387029125,"possibility":"24.5"},{"date":"2026-03-01T17:44:19.125950","timestamp":1772387059125,"possibility":"24.8"},{"date":"2026-03-01T17:44:49.125950","timestamp":1772387089125,"possibility":"24.8"},{"date":"2026-03-01T17:45:19.125950","timestamp":1772387119125,"possibility":"25.3"},{"date":"2026-03-01T17:45:49.125950","timestamp":1772387149125,"possibility":"24.3"},{"date":"2026-03-01T17:46:19.125950","timestamp":1772387179125,"possibility":"24.7"},{"date":"2026-03-01T17:46:49.125950","timestamp":1772387209125,"possibility":"24.5"},{"date":"2026-03-01T17:47:19.125950","timestamp":1772387239125,"possibility":"23.3"},{"date":"2026-03-01T17:47:49.125950","timestamp":1772387269125,"possibility":"22.9"},{"date":"2026-03-01T17:48:19.125950","timestamp":1772387299125,"possibility":"23.4"},{"date":"2026-03-01T17:48:49.125950","timestamp":1772387329125,"possibility":"24.2"},{"date":"2026-03-01T17:49:19.125950","timestamp":1772387359125,"possibility":"23.9"},{"date":"2026-03-01T17:49:49.125950","timestamp":1772387389125,"possibility":"24.4"}],"count":30}},{"id":"member_012","name":"정이한","party":"개혁신당","district":"부산광역시장","timestamp":1772387389627,"analyzedAt":"2026-03-01T17:49:49.627634","electionPossibility":"23.65","electionPossibilityPercent":"23.7","possibilityChange":"0.48","possibilityChangePercent":"0.5","scores":{"achievement":"5.0","activity":"3.3","policy":"0.0","publicImage":"21.2","poll":"50.0"},"polls":{"count":0,"data":[]},"snsAnalysis":{"totalMentions":1,"sentiment":{"positive":0,"neutral":1,"negative":0},"sentimentScore":"30.0","topMentions":["정이한","대변인이","부산시장","출마를","선언했다"],"engagementTrend":"하락","sentimentRatio":{"positive":"0.0","neutral":"100.0","negative":"0.0"}},"pressReports":{"count":1,"sentimentAverage":"0.0"},"trends":{"recent":[{"date":"2026-03-01T17:35:19.627020","timestamp":1772386519627,"possibility":"24.4"},{"date":"2026-03-01T17:35:49.627020","timestamp":1772386549627,"possibility":"24.4"},{"date":"2026-03-01T17:36:19.627020","timestamp":1772386579627,"possibility":"25.7"},{"date":"2026-03-01T17:36:49.627020","timestamp":1772386609627,"possibility":"24.6"},{"date":"2026-03-01T17:37:19.627020","timestamp":1772386639627,"possibility":"25.6"},{"date":"2026-03-01T17:37:49.627020","timestamp":1772386669627,"possibility":"25.0"},{"date":"2026-03-01T17:38:19.627020","timestamp":1772386699627,"possibility":"24.9"},{"date":"2026-03-01T17:38:49.627020","timestamp":1772386729627,"possibility":"24.9"},{"date":"2026-03-01T17:39:19.627020","timestamp":1772386759627,"possibility":"25.1"},{"date":"2026-03-01T17:39:49.627020","timestamp":1772386789627,"possibility":"25.6"},{"date":"2026-03-01T17:40:19.627020","timestamp":1772386819627,"possibility":"25.6"},{"date":"2026-03-01T17:40:49.627020","timestamp":1772386849627,"possibility":"26.2"},{"date":"2026-03-01T17:41:19.627020","timestamp":1772386879627,"possibility":"25.8"},{"date":"2026-03-01T17:41:49.627020","timestamp":1772386909627,"possibility":"26.5"},{"date":"2026-03-01T17:42:19.627020","timestamp":1772386939627,"possibility":"26.6"},{"date":"2026-03-01T17:42:49.627020","timestamp":1772386969627,"possibility":"25.5"},{"date":"2026-03-01T17:43:19.627020","timestamp":1772386999627,"possibility":"26.1"},{"date":"2026-03-01T17:43:49.627020","timestamp":1772387029627,"possibility":"25.3"},{"date":"2026-03-01T17:44:19.627020","timestamp":1772387059627,"possibility":"24.8"},{"date":"2026-03-01T17:44:49.627020","timestamp":1772387089627,"possibility":"23.7"},{"date":"2026-03-01T17:45:19.627020","timestamp":1772387119627,"possibility":"24.4"},{"date":"2026-03-01T17:45:49.627020","timestamp":1772387149627,"possibility":"23.7"},{"date":"2026-03-01T17:46:19.627020","timestamp":1772387179627,"possibility":"24.6"},{"date":"2026-03-01T17:46:49.627020","timestamp":1772387209627,"possibility":"23.2"},{"date":"2026-03-01T17:47:19.627020","timestamp":1772387239627,"possibility":"24.3"},{"date":"2026-03-01T17:47:49.627020","timestamp":1772387269627,"possibility":"23.6"},{"date":"2026-03-01T17:48:19.627020","timestamp":1772387299627,"possibility":"25.1"},{"date":"2026-03-01T17:48:49.627020","timestamp":1772387329627,"possibility":"23.6"},{"date":"2026-03-01T17:49:19.627020","timestamp":1772387359627,"possibility":"23.2"},{"date":"2026-03-01T17:49:49.627020","timestamp":1772387389627,"possibility":"22.5"}],"count":30}},{"id":"member_013","name":"이강덕","party":"무소속","district":"경북도지사","timestamp":1772387390128,"analyzedAt":"2026-03-01T17:49:50.128442","electionPossibility":"24.71","electionPossibilityPercent":"24.7","possibilityChange":"0.49","possibilityChangePercent":"0.5","scores":{"achievement":"5.0","activity":"3.3","policy":"0.0","publicImage":"21.2","poll":"50.0"},"polls":{"count":0,"data":[]},"snsAnalysis":{"totalMentions":1,"sentiment":{"positive":0,"neutral":1,"negative":0},"sentimentScore":"30.0","topMentions":["이강덕","포항시장이","경북도지사","출마를","선언했다"],"engagementTrend":"하락","sentimentRatio":{"positive":"0.0","neutral":"100.0","negative":"0.0"}},"pressReports":{"count":1,"sentimentAverage":"0.0"},"trends":{"recent":[{"date":"2026-03-01T17:35:20.127954","timestamp":1772386520127,"possibility":"24.4"},{"date":"2026-03-01T17:35:50.127954","timestamp":1772386550127,"possibility":"24.7"},{"date":"2026-03-01T17:36:20.127954","timestamp":1772386580127,"possibility":"24.1"},{"date":"2026-03-01T17:36:50.127954","timestamp":1772386610127,"possibility":"22.7"},{"date":"2026-03-01T17:37:20.127954","timestamp":1772386640127,"possibility":"23.9"},{"date":"2026-03-01T17:37:50.127954","timestamp":1772386670127,"possibility":"23.9"},{"date":"2026-03-01T17:38:20.127954","timestamp":1772386700127,"possibility":"24.7"},{"date":"2026-03-01T17:38:50.127954","timestamp":1772386730127,"possibility":"26.1"},{"date":"2026-03-01T17:39:20.127954","timestamp":1772386760127,"possibility":"24.7"},{"date":"2026-03-01T17:39:50.127954","timestamp":1772386790127,"possibility":"23.7"},{"date":"2026-03-01T17:40:20.127954","timestamp":1772386820127,"possibility":"24.9"},{"date":"2026-03-01T17:40:50.127954","timestamp":1772386850127,"possibility":"24.7"},{"date":"2026-03-01T17:41:20.127954","timestamp":1772386880127,"possibility":"23.3"},{"date":"2026-03-01T17:41:50.127954","timestamp":1772386910127,"possibility":"23.4"},{"date":"2026-03-01T17:42:20.127954","timestamp":1772386940127,"possibility":"22.9"},{"date":"2026-03-01T17:42:50.127954","timestamp":1772386970127,"possibility":"23.0"},{"date":"2026-03-01T17:43:20.127954","timestamp":1772387000127,"possibility":"21.7"},{"date":"2026-03-01T17:43:50.127954","timestamp":1772387030127,"possibility":"22.9"},{"date":"2026-03-01T17:44:20.127954","timestamp":1772387060127,"possibility":"24.2"},{"date":"2026-03-01T17:44:50.127954","timestamp":1772387090127,"possibility":"25.2"},{"date":"2026-03-01T17:45:20.127954","timestamp":1772387120127,"possibility":"25.2"},{"date":"2026-03-01T17:45:50.127954","timestamp":1772387150127,"possibility":"24.1"},{"date":"2026-03-01T17:46:20.127954","timestamp":1772387180127,"possibility":"25.3"},{"date":"2026-03-01T17:46:50.127954","timestamp":1772387210127,"possibility":"25.1"},{"date":"2026-03-01T17:47:20.127954","timestamp":1772387240127,"possibility":"24.6"},{"date":"2026-03-01T17:47:50.127954","timestamp":1772387270127,"possibility":"24.2"},{"date":"2026-03-01T17:48:20.127954","timestamp":1772387300127,"possibility":"24.2"},{"date":"2026-03-01T17:48:50.127954","timestamp":1772387330127,"possibility":"25.4"},{"date":"2026-03-01T17:49:20.127954","timestamp":1772387360127,"possibility":"24.2"},{"date":"2026-03-01T17:49:50.127954","timestamp":1772387390127,"possibility":"25.3"}],"count":30}},{"id":"member_014","name":"김재원","party":"국민의힘","district":"경북도지사","timestamp":1772387390629,"analyzedAt":"2026-03-01T17:49:50.629364","electionPossibility":"22.21","electionPossibilityPercent":"22.2","possibilityChange":"0.83","possibilityChangePercent":"0.8","scores":{"achievement":"5.0","activity":"3.3","policy":"0.0","publicImage":"21.2","poll":"50.0"},"polls":{"count":0,"data":[]},"snsAnalysis":{"totalMentions":1,"sentiment":{"positive":0,"neutral":1,"negative":0},"sentimentScore":"30.0","topMentions":["김재원","최고위원이","경북도지사","출마를","선언했다"],"engagementTrend":"하락","sentimentRatio":{"positive":"0.0","neutral":"100.0","negative":"0.0"}},"pressReports":{"count":1,"sentimentAverage":"0.0"},"trends":{"recent":[{"date":"2026-03-01T17:35:20.628908","timestamp":1772386520628,"possibility":"24.4"},{"date":"2026-03-01T17:35:50.628908","timestamp":1772386550628,"possibility":"24.7"},{"date":"2026-03-01T17:36:20.628908","timestamp":1772386580628,"possibility":"26.2"},{"date":"2026-03-01T17:36:50.628908","timestamp":1772386610628,"possibility":"25.9"},{"date":"2026-03-01T17:37:20.628908","timestamp":1772386640628,"possibility":"25.6"},{"date":"2026-03-01T17:37:50.628908","timestamp":1772386670628,"possibility":"25.2"},{"date":"2026-03-01T17:38:20.628908","timestamp":1772386700628,"possibility":"26.5"},{"date":"2026-03-01T17:38:50.628908","timestamp":1772386730628,"possibility":"25.0"},{"date":"2026-03-01T17:39:20.628908","timestamp":1772386760628,"possibility":"26.2"},{"date":"2026-03-01T17:39:50.628908","timestamp":1772386790628,"possibility":"25.4"},{"date":"2026-03-01T17:40:20.628908","timestamp":1772386820628,"possibility":"25.1"},{"date":"2026-03-01T17:40:50.628908","timestamp":1772386850628,"possibility":"23.6"},{"date":"2026-03-01T17:41:20.628908","timestamp":1772386880628,"possibility":"24.9"},{"date":"2026-03-01T17:41:50.628908","timestamp":1772386910628,"possibility":"23.9"},{"date":"2026-03-01T17:42:20.628908","timestamp":1772386940628,"possibility":"23.9"},{"date":"2026-03-01T17:42:50.628908","timestamp":1772386970628,"possibility":"22.5"},{"date":"2026-03-01T17:43:20.628908","timestamp":1772387000628,"possibility":"21.9"},{"date":"2026-03-01T17:43:50.628908","timestamp":1772387030628,"possibility":"21.0"},{"date":"2026-03-01T17:44:20.628908","timestamp":1772387060628,"possibility":"21.3"},{"date":"2026-03-01T17:44:50.628908","timestamp":1772387090628,"possibility":"21.8"},{"date":"2026-03-01T17:45:20.628908","timestamp":1772387120628,"possibility":"22.3"},{"date":"2026-03-01T17:45:50.628908","timestamp":1772387150628,"possibility":"21.2"},{"date":"2026-03-01T17:46:20.628908","timestamp":1772387180628,"possibility":"21.1"},{"date":"2026-03-01T17:46:50.628908","timestamp":1772387210628,"possibility":"22.5"},{"date":"2026-03-01T17:47:20.628908","timestamp":1772387240628,"possibility":"23.0"},{"date":"2026-03-01T17:47:50.628908","timestamp":1772387270628,"possibility":"23.8"},{"date":"2026-03-01T17:48:20.628908","timestamp":1772387300628,"possibility":"22.5"},{"date":"2026-03-01T17:48:50.628908","timestamp":1772387330628,"possibility":"21.4"},{"date":"2026-03-01T17:49:20.628908","timestamp":1772387360628,"possibility":"21.4"},{"date":"2026-03-01T17:49:50.628908","timestamp":1772387390628,"possibility":"20.9"}],"count":30}},{"id":"member_015","name":"주호영","party":"국민의힘","district":"대구광역시장","timestamp":1772387391130,"analyzedAt":"2026-03-01T17:49:51.130426","electionPossibility":"24.77","electionPossibilityPercent":"24.8","possibilityChange":"-0.75","possibilityChangePercent":"-0.8","scores":{"achievement":"5.0","activity":"3.3","policy":"0.0","publicImage":"21.2","poll":"50.0"},"polls":{"count":0,"data":[]},"snsAnalysis":{"totalMentions":1,"sentiment":{"positive":0,"neutral":1,"negative":0},"sentimentScore":"30.0","topMentions":["주호영","의원이","대구시장","출마를","선언했다"],"engagementTrend":"하락","sentimentRatio":{"positive":"0.0","neutral":"100.0","negative":"0.0"}},"pressReports":{"count":1,"sentimentAverage":"0.0"},"trends":{"recent":[{"date":"2026-03-01T17:35:21.129981","timestamp":1772386521129,"possibility":"24.4"},{"date":"2026-03-01T17:35:51.129981","timestamp":1772386551129,"possibility":"24.7"},{"date":"2026-03-01T17:36:21.129981","timestamp":1772386581129,"possibility":"25.6"},{"date":"2026-03-01T17:36:51.129981","timestamp":1772386611129,"possibility":"25.9"},{"date":"2026-03-01T17:37:21.129981","timestamp":1772386641129,"possibility":"27.2"},{"date":"2026-03-01T17:37:51.129981","timestamp":1772386671129,"possibility":"26.7"},{"date":"2026-03-01T17:38:21.129981","timestamp":1772386701129,"possibility":"27.2"},{"date":"2026-03-01T17:38:51.129981","timestamp":1772386731129,"possibility":"26.4"},{"date":"2026-03-01T17:39:21.129981","timestamp":1772386761129,"possibility":"27.4"},{"date":"2026-03-01T17:39:51.129981","timestamp":1772386791129,"possibility":"26.0"},{"date":"2026-03-01T17:40:21.129981","timestamp":1772386821129,"possibility":"24.7"},{"date":"2026-03-01T17:40:51.129981","timestamp":1772386851129,"possibility":"25.9"},{"date":"2026-03-01T17:41:21.129981","timestamp":1772386881129,"possibility":"25.2"},{"date":"2026-03-01T17:41:51.129981","timestamp":1772386911129,"possibility":"23.9"},{"date":"2026-03-01T17:42:21.129981","timestamp":1772386941129,"possibility":"22.9"},{"date":"2026-03-01T17:42:51.129981","timestamp":1772386971129,"possibility":"21.9"},{"date":"2026-03-01T17:43:21.129981","timestamp":1772387001129,"possibility":"21.2"},{"date":"2026-03-01T17:43:51.129981","timestamp":1772387031129,"possibility":"22.9"},{"date":"2026-03-01T17:44:21.129981","timestamp":1772387061129,"possibility":"22.7"},{"date":"2026-03-01T17:44:51.129981","timestamp":1772387091129,"possibility":"23.5"},{"date":"2026-03-01T17:45:21.129981","timestamp":1772387121129,"possibility":"23.2"},{"date":"2026-03-01T17:45:51.129981","timestamp":1772387151129,"possibility":"23.2"},{"date":"2026-03-01T17:46:21.129981","timestamp":1772387181129,"possibility":"23.3"},{"date":"2026-03-01T17:46:51.129981","timestamp":1772387211129,"possibility":"24.1"},{"date":"2026-03-01T17:47:21.129981","timestamp":1772387241129,"possibility":"23.3"},{"date":"2026-03-01T17:47:51.129981","timestamp":1772387271129,"possibility":"24.2"},{"date":"2026-03-01T17:48:21.129981","timestamp":1772387301129,"possibility":"24.9"},{"date":"2026-03-01T17:48:51.129981","timestamp":1772387331129,"possibility":"26.3"},{"date":"2026-03-01T17:49:21.129981","timestamp":1772387361129,"possibility":"25.5"},{"date":"2026-03-01T17:49:51.129981","timestamp":1772387391129,"possibility":"25.1"}],"count":30}},{"id":"member_016","name":"윤재옥","party":"국민의힘","district":"대구광역시장","timestamp":1772387391631,"analyzedAt":"2026-03-01T17:49:51.631402","electionPossibility":"28.73","electionPossibilityPercent":"28.7","possibilityChange":"0.68","possibilityChangePercent":"0.7","scores":{"achievement":"5.0","activity":"3.3","policy":"0.0","publicImage":"21.2","poll":"50.0"},"polls":{"count":0,"data":[]},"snsAnalysis":{"totalMentions":1,"sentiment":{"positive":0,"neutral":1,"negative":0},"sentimentScore":"30.0","topMentions":["윤재옥","의원이","대구시장","출마를","선언했다"],"engagementTrend":"하락","sentimentRatio":{"positive":"0.0","neutral":"100.0","negative":"0.0"}},"pressReports":{"count":1,"sentimentAverage":"0.0"},"trends":{"recent":[{"date":"2026-03-01T17:35:21.630958","timestamp":1772386521630,"possibility":"24.4"},{"date":"2026-03-01T17:35:51.630958","timestamp":1772386551630,"possibility":"24.3"},{"date":"2026-03-01T17:36:21.630958","timestamp":1772386581630,"possibility":"25.0"},{"date":"2026-03-01T17:36:51.630958","timestamp":1772386611630,"possibility":"26.2"},{"date":"2026-03-01T17:37:21.630958","timestamp":1772386641630,"possibility":"25.6"},{"date":"2026-03-01T17:37:51.630958","timestamp":1772386671630,"possibility":"25.1"},{"date":"2026-03-01T17:38:21.630958","timestamp":1772386701630,"possibility":"25.0"},{"date":"2026-03-01T17:38:51.630958","timestamp":1772386731630,"possibility":"24.2"},{"date":"2026-03-01T17:39:21.630958","timestamp":1772386761630,"possibility":"22.8"},{"date":"2026-03-01T17:39:51.630958","timestamp":1772386791630,"possibility":"23.7"},{"date":"2026-03-01T17:40:21.630958","timestamp":1772386821630,"possibility":"23.5"},{"date":"2026-03-01T17:40:51.630958","timestamp":1772386851630,"possibility":"25.0"},{"date":"2026-03-01T17:41:21.630958","timestamp":1772386881630,"possibility":"25.5"},{"date":"2026-03-01T17:41:51.630958","timestamp":1772386911630,"possibility":"26.7"},{"date":"2026-03-01T17:42:21.630958","timestamp":1772386941630,"possibility":"27.6"},{"date":"2026-03-01T17:42:51.630958","timestamp":1772386971630,"possibility":"26.9"},{"date":"2026-03-01T17:43:21.630958","timestamp":1772387001630,"possibility":"26.4"},{"date":"2026-03-01T17:43:51.630958","timestamp":1772387031630,"possibility":"27.1"},{"date":"2026-03-01T17:44:21.630958","timestamp":1772387061630,"possibility":"28.3"},{"date":"2026-03-01T17:44:51.630958","timestamp":1772387091630,"possibility":"27.8"},{"date":"2026-03-01T17:45:21.630958","timestamp":1772387121630,"possibility":"27.7"},{"date":"2026-03-01T17:45:51.630958","timestamp":1772387151630,"possibility":"27.7"},{"date":"2026-03-01T17:46:21.630958","timestamp":1772387181630,"possibility":"28.7"},{"date":"2026-03-01T17:46:51.630958","timestamp":1772387211630,"possibility":"29.3"},{"date":"2026-03-01T17:47:21.630958","timestamp":1772387241630,"possibility":"28.6"},{"date":"2026-03-01T17:47:51.630958","timestamp":1772387271630,"possibility":"29.4"},{"date":"2026-03-01T17:48:21.630958","timestamp":1772387301630,"possibility":"29.8"},{"date":"2026-03-01T17:48:51.630958","timestamp":1772387331630,"possibility":"28.6"},{"date":"2026-03-01T17:49:21.630958","timestamp":1772387361630,"possibility":"28.0"},{"date":"2026-03-01T17:49:51.630958","timestamp":1772387391630,"possibility":"27.3"}],"count":30}},{"id":"member_017","name":"추경호","party":"국민의힘","district":"대구광역시장","timestamp":1772387392132,"analyzedAt":"2026-03-01T17:49:52.132333","electionPossibility":"24.69","electionPossibilityPercent":"24.7","possibilityChange":"-0.50","possibilityChangePercent":"-0.5","scores":{"achievement":"5.0","activity":"3.3","policy":"0.0","publicImage":"21.2","poll":"50.0"},"polls":{"count":0,"data":[]},"snsAnalysis":{"totalMentions":1,"sentiment":{"positive":0,"neutral":1,"negative":0},"sentimentScore":"30.0","topMentions":["추경호","의원이","대구시장","출마를","선언했다"],"engagementTrend":"하락","sentimentRatio":{"positive":"0.0","neutral":"100.0","negative":"0.0"}},"pressReports":{"count":1,"sentimentAverage":"0.0"},"trends":{"recent":[{"date":"2026-03-01T17:35:22.131913","timestamp":1772386522131,"possibility":"24.4"},{"date":"2026-03-01T17:35:52.131913","timestamp":1772386552131,"possibility":"24.8"},{"date":"2026-03-01T17:36:22.131913","timestamp":1772386582131,"possibility":"24.7"},{"date":"2026-03-01T17:36:52.131913","timestamp":1772386612131,"possibility":"23.4"},{"date":"2026-03-01T17:37:22.131913","timestamp":1772386642131,"possibility":"24.9"},{"date":"2026-03-01T17:37:52.131913","timestamp":1772386672131,"possibility":"25.7"},{"date":"2026-03-01T17:38:22.131913","timestamp":1772386702131,"possibility":"24.4"},{"date":"2026-03-01T17:38:52.131913","timestamp":1772386732131,"possibility":"25.7"},{"date":"2026-03-01T17:39:22.131913","timestamp":1772386762131,"possibility":"25.2"},{"date":"2026-03-01T17:39:52.131913","timestamp":1772386792131,"possibility":"25.1"},{"date":"2026-03-01T17:40:22.131913","timestamp":1772386822131,"possibility":"24.2"},{"date":"2026-03-01T17:40:52.131913","timestamp":1772386852131,"possibility":"23.8"},{"date":"2026-03-01T17:41:22.131913","timestamp":1772386882131,"possibility":"24.2"},{"date":"2026-03-01T17:41:52.131913","timestamp":1772386912131,"possibility":"24.7"},{"date":"2026-03-01T17:42:22.131913","timestamp":1772386942131,"possibility":"25.4"},{"date":"2026-03-01T17:42:52.131913","timestamp":1772386972131,"possibility":"25.3"},{"date":"2026-03-01T17:43:22.131913","timestamp":1772387002131,"possibility":"26.4"},{"date":"2026-03-01T17:43:52.131913","timestamp":1772387032131,"possibility":"27.3"},{"date":"2026-03-01T17:44:22.131913","timestamp":1772387062131,"possibility":"26.8"},{"date":"2026-03-01T17:44:52.131913","timestamp":1772387092131,"possibility":"27.3"},{"date":"2026-03-01T17:45:22.131913","timestamp":1772387122131,"possibility":"25.9"},{"date":"2026-03-01T17:45:52.131913","timestamp":1772387152131,"possibility":"24.6"},{"date":"2026-03-01T17:46:22.131913","timestamp":1772387182131,"possibility":"24.5"},{"date":"2026-03-01T17:46:52.131913","timestamp":1772387212131,"possibility":"24.3"},{"date":"2026-03-01T17:47:22.131913","timestamp":1772387242131,"possibility":"23.8"},{"date":"2026-03-01T17:47:52.131913","timestamp":1772387272131,"possibility":"23.7"},{"date":"2026-03-01T17:48:22.131913","timestamp":1772387302131,"possibility":"25.2"},{"date":"2026-03-01T17:48:52.131913","timestamp":1772387332131,"possibility":"26.5"},{"date":"2026-03-01T17:49:22.131913","timestamp":1772387362131,"possibility":"25.2"},{"date":"2026-03-01T17:49:52.131913","timestamp":1772387392131,"possibility":"24.1"}],"count":30}},{"id":"member_018","name":"이현규","party":"무소속","district":"경남 창원시장","timestamp":1772387392633,"analyzedAt":"2026-03-01T17:49:52.633442","electionPossibility":"25.29","electionPossibilityPercent":"25.3","possibilityChange":"-0.57","possibilityChangePercent":"-0.6","scores":{"achievement":"5.0","activity":"3.3","policy":"0.0","publicImage":"21.2","poll":"50.0"},"polls":{"count":0,"data":[]},"snsAnalysis":{"totalMentions":1,"sentiment":{"positive":0,"neutral":1,"negative":0},"sentimentScore":"30.0","topMentions":["이현규","부시장이","창원시장","출마를","선언했다"],"engagementTrend":"하락","sentimentRatio":{"positive":"0.0","neutral":"100.0","negative":"0.0"}},"pressReports":{"count":1,"sentimentAverage":"0.0"},"trends":{"recent":[{"date":"2026-03-01T17:35:22.632947","timestamp":1772386522632,"possibility":"24.4"},{"date":"2026-03-01T17:35:52.632947","timestamp":1772386552632,"possibility":"23.5"},{"date":"2026-03-01T17:36:22.632947","timestamp":1772386582632,"possibility":"24.8"},{"date":"2026-03-01T17:36:52.632947","timestamp":1772386612632,"possibility":"24.3"},{"date":"2026-03-01T17:37:22.632947","timestamp":1772386642632,"possibility":"23.3"},{"date":"2026-03-01T17:37:52.632947","timestamp":1772386672632,"possibility":"22.0"},{"date":"2026-03-01T17:38:22.632947","timestamp":1772386702632,"possibility":"23.6"},{"date":"2026-03-01T17:38:52.632947","timestamp":1772386732632,"possibility":"24.8"},{"date":"2026-03-01T17:39:22.632947","timestamp":1772386762632,"possibility":"23.9"},{"date":"2026-03-01T17:39:52.632947","timestamp":1772386792632,"possibility":"23.4"},{"date":"2026-03-01T17:40:22.632947","timestamp":1772386822632,"possibility":"22.2"},{"date":"2026-03-01T17:40:52.632947","timestamp":1772386852632,"possibility":"23.5"},{"date":"2026-03-01T17:41:22.632947","timestamp":1772386882632,"possibility":"24.0"},{"date":"2026-03-01T17:41:52.632947","timestamp":1772386912632,"possibility":"25.3"},{"date":"2026-03-01T17:42:22.632947","timestamp":1772386942632,"possibility":"24.7"},{"date":"2026-03-01T17:42:52.632947","timestamp":1772386972632,"possibility":"24.4"},{"date":"2026-03-01T17:43:22.632947","timestamp":1772387002632,"possibility":"25.3"},{"date":"2026-03-01T17:43:52.632947","timestamp":1772387032632,"possibility":"25.1"},{"date":"2026-03-01T17:44:22.632947","timestamp":1772387062632,"possibility":"26.2"},{"date":"2026-03-01T17:44:52.632947","timestamp":1772387092632,"possibility":"27.5"},{"date":"2026-03-01T17:45:22.632947","timestamp":1772387122632,"possibility":"27.1"},{"date":"2026-03-01T17:45:52.632947","timestamp":1772387152632,"possibility":"27.0"},{"date":"2026-03-01T17:46:22.632947","timestamp":1772387182632,"possibility":"25.7"},{"date":"2026-03-01T17:46:52.632947","timestamp":1772387212632,"possibility":"24.5"},{"date":"2026-03-01T17:47:22.632947","timestamp":1772387242632,"possibility":"25.1"},{"date":"2026-03-01T17:47:52.632947","timestamp":1772387272632,"possibility":"25.0"},{"date":"2026-03-01T17:48:22.632947","timestamp":1772387302632,"possibility":"26.3"},{"date":"2026-03-01T17:48:52.632947","timestamp":1772387332632,"possibility":"25.0"},{"date":"2026-03-01T17:49:22.632947","timestamp":1772387362632,"possibility":"25.9"},{"date":"2026-03-01T17:49:52.632947","timestamp":1772387392632,"possibility":"25.3"}],"count":30}},{"id":"member_019","name":"김수우","party":"무소속","district":"경기 평택시장","timestamp":1772387393134,"analyzedAt":"2026-03-01T17:49:53.134467","electionPossibility":"22.91","electionPossibilityPercent":"22.9","possibilityChange":"-0.26","possibilityChangePercent":"-0.3","scores":{"achievement":"5.0","activity":"3.3","policy":"0.0","publicImage":"21.2","poll":"50.0"},"polls":{"count":0,"data":[]},"snsAnalysis":{"totalMentions":1,"sentiment":{"positive":0,"neutral":1,"negative":0},"sentimentScore":"30.0","topMentions":["김수우","시의원이","평택시장","출마를","선언했다"],"engagementTrend":"하락","sentimentRatio":{"positive":"0.0","neutral":"100.0","negative":"0.0"}},"pressReports":{"count":1,"sentimentAverage":"0.0"},"trends":{"recent":[{"date":"2026-03-01T17:35:23.133964","timestamp":1772386523133,"possibility":"24.4"},{"date":"2026-03-01T17:35:53.133964","timestamp":1772386553133,"possibility":"23.3"},{"date":"2026-03-01T17:36:23.133964","timestamp":1772386583133,"possibility":"22.6"},{"date":"2026-03-01T17:36:53.133964","timestamp":1772386613133,"possibility":"21.3"},{"date":"2026-03-01T17:37:23.133964","timestamp":1772386643133,"possibility":"21.3"},{"date":"2026-03-01T17:37:53.133964","timestamp":1772386673133,"possibility":"20.5"},{"date":"2026-03-01T17:38:23.133964","timestamp":1772386703133,"possibility":"20.9"},{"date":"2026-03-01T17:38:53.133964","timestamp":1772386733133,"possibility":"20.6"},{"date":"2026-03-01T17:39:23.133964","timestamp":1772386763133,"possibility":"20.2"},{"date":"2026-03-01T17:39:53.133964","timestamp":1772386793133,"possibility":"21.1"},{"date":"2026-03-01T17:40:23.133964","timestamp":1772386823133,"possibility":"22.1"},{"date":"2026-03-01T17:40:53.133964","timestamp":1772386853133,"possibility":"22.5"},{"date":"2026-03-01T17:41:23.133964","timestamp":1772386883133,"possibility":"21.6"},{"date":"2026-03-01T17:41:53.133964","timestamp":1772386913133,"possibility":"21.0"},{"date":"2026-03-01T17:42:23.133964","timestamp":1772386943133,"possibility":"22.3"},{"date":"2026-03-01T17:42:53.133964","timestamp":1772386973133,"possibility":"22.0"},{"date":"2026-03-01T17:43:23.133964","timestamp":1772387003133,"possibility":"20.7"},{"date":"2026-03-01T17:43:53.133964","timestamp":1772387033133,"possibility":"21.8"},{"date":"2026-03-01T17:44:23.133964","timestamp":1772387063133,"possibility":"21.7"},{"date":"2026-03-01T17:44:53.133964","timestamp":1772387093133,"possibility":"21.4"},{"date":"2026-03-01T17:45:23.133964","timestamp":1772387123133,"possibility":"21.8"},{"date":"2026-03-01T17:45:53.133964","timestamp":1772387153133,"possibility":"22.7"},{"date":"2026-03-01T17:46:23.133964","timestamp":1772387183133,"possibility":"22.3"},{"date":"2026-03-01T17:46:53.133964","timestamp":1772387213133,"possibility":"22.8"},{"date":"2026-03-01T17:47:23.133964","timestamp":1772387243133,"possibility":"23.3"},{"date":"2026-03-01T17:47:53.133964","timestamp":1772387273133,"possibility":"23.0"},{"date":"2026-03-01T17:48:23.133964","timestamp":1772387303133,"possibility":"22.1"},{"date":"2026-03-01T17:48:53.133964","timestamp":1772387333133,"possibility":"21.5"},{"date":"2026-03-01T17:49:23.133964","timestamp":1772387363133,"possibility":"23.2"},{"date":"2026-03-01T17:49:53.133964","timestamp":1772387393133,"possibility":"24.4"}],"count":30}},{"id":"member_020","name":"이춘희","party":"더불어민주당","district":"세종특별자치시장","timestamp":1772387393635,"analyzedAt":"2026-03-01T17:49:53.635453","electionPossibility":"25.35","electionPossibilityPercent":"25.3","possibilityChange":"0.44","possibilityChangePercent":"0.4","scores":{"achievement":"5.0","activity":"3.3","policy":"0.0","publicImage":"21.2","poll":"50.0"},"polls":{"count":0,"data":[]},"snsAnalysis":{"totalMentions":1,"sentiment":{"positive":0,"neutral":1,"negative":0},"sentimentScore":"30.0","topMentions":["이춘희","세종시장이","세종시장","출마를","선언했다"],"engagementTrend":"하락","sentimentRatio":{"positive":"0.0","neutral":"100.0","negative":"0.0"}},"pressReports":{"count":1,"sentimentAverage":"0.0"},"trends":{"recent":[{"date":"2026-03-01T17:35:23.634951","timestamp":1772386523634,"possibility":"24.4"},{"date":"2026-03-01T17:35:53.634951","timestamp":1772386553634,"possibility":"25.1"},{"date":"2026-03-01T17:36:23.634951","timestamp":1772386583634,"possibility":"24.9"},{"date":"2026-03-01T17:36:53.634951","timestamp":1772386613634,"possibility":"25.5"},{"date":"2026-03-01T17:37:23.634951","timestamp":1772386643634,"possibility":"26.4"},{"date":"2026-03-01T17:37:53.634951","timestamp":1772386673634,"possibility":"25.6"},{"date":"2026-03-01T17:38:23.634951","timestamp":1772386703634,"possibility":"26.0"},{"date":"2026-03-01T17:38:53.634951","timestamp":1772386733634,"possibility":"24.6"},{"date":"2026-03-01T17:39:23.634951","timestamp":1772386763634,"possibility":"24.8"},{"date":"2026-03-01T17:39:53.634951","timestamp":1772386793634,"possibility":"25.2"},{"date":"2026-03-01T17:40:23.634951","timestamp":1772386823634,"possibility":"24.4"},{"date":"2026-03-01T17:40:53.634951","timestamp":1772386853634,"possibility":"25.2"},{"date":"2026-03-01T17:41:23.634951","timestamp":1772386883634,"possibility":"25.5"},{"date":"2026-03-01T17:41:53.634951","timestamp":1772386913634,"possibility":"24.0"},{"date":"2026-03-01T17:42:23.634951","timestamp":1772386943634,"possibility":"24.5"},{"date":"2026-03-01T17:42:53.634951","timestamp":1772386973634,"possibility":"25.1"},{"date":"2026-03-01T17:43:23.634951","timestamp":1772387003634,"possibility":"26.5"},{"date":"2026-03-01T17:43:53.634951","timestamp":1772387033634,"possibility":"26.3"},{"date":"2026-03-01T17:44:23.634951","timestamp":1772387063634,"possibility":"26.0"},{"date":"2026-03-01T17:44:53.634951","timestamp":1772387093634,"possibility":"26.3"},{"date":"2026-03-01T17:45:23.634951","timestamp":1772387123634,"possibility":"27.6"},{"date":"2026-03-01T17:45:53.634951","timestamp":1772387153634,"possibility":"27.1"},{"date":"2026-03-01T17:46:23.634951","timestamp":1772387183634,"possibility":"25.4"},{"date":"2026-03-01T17:46:53.634951","timestamp":1772387213634,"possibility":"24.9"},{"date":"2026-03-01T17:47:23.634951","timestamp":1772387243634,"possibility":"26.1"},{"date":"2026-03-01T17:47:53.634951","timestamp":1772387273634,"possibility":"25.0"},{"date":"2026-03-01T17:48:23.634951","timestamp":1772387303634,"possibility":"25.4"},{"date":"2026-03-01T17:48:53.634951","timestamp":1772387333634,"possibility":"26.5"},{"date":"2026-03-01T17:49:23.634951","timestamp":1772387363634,"possibility":"24.9"},{"date":"2026-03-01T17:49:53.634951","timestamp":1772387393634,"possibility":"24.6"}],"count":30}}],"totalMembers":20,"lastUpdated":"2026-03-01T17:49:53.635743"}